streamstats/__init__.py
streamstats/utils.py
streamstats/watershed.py
streamstats-0.1.5.dist-info/AUTHORS.rst
streamstats-0.1.5.dist-info/LICENSE
streamstats-0.1.5.dist-info/METADATA
streamstats-0.1.5.dist-info/WHEEL
streamstats-0.1.5.dist-info/top_level.txt
streamstats-0.1.5.dist-info/RECORD
