Metadata-Version: 2.1
Name: streamstats
Version: 0.1.5
Summary: Python package for using the USGS StreamStats API.
Home-page: https://github.com/earthlab/streamstats
Author: Maxwell B. Joseph
Author-email: maxwell.b.joseph@colorado.edu
License: MIT license
Keywords: streamstats
Platform: UNKNOWN
Classifier: Development Status :: 2 - Pre-Alpha
Classifier: Intended Audience :: Developers
Classifier: License :: OSI Approved :: MIT License
Classifier: Natural Language :: English
Classifier: Programming Language :: Python :: 3
Classifier: Programming Language :: Python :: 3.4
Classifier: Programming Language :: Python :: 3.5
Classifier: Programming Language :: Python :: 3.6
Classifier: Programming Language :: Python :: 3.7
Requires-Dist: geopy
Requires-Dist: requests
Requires-Dist: urllib3
